{
  "title": "Dickhead",
  "description": "In a post apocalyptic world, a young girl defends herself from bandits using a penis monster contract.",
  "artist": "JerzM",
  "author": "JerzM",
  "cover": "",
  "chapters": {
    "1": {
      "title": "Chapter1 : Our phantom dreams",
      "volume": "1",
      "last_updated": "1709519652",
      "groups": {
        "": [
          "https://drive.usercontent.google.com/download?id=10MQYqnrr5cchbnrrsZj-ijRg7rIb9w5U",
          "https://drive.usercontent.google.com/download?id=18JvaOtdfzfSi5SHSUzBHOmJM1MjdvUd3",
          "https://drive.usercontent.google.com/download?id=1JK_NXxCq_GhcavRTRODMKwgO6i18UNv0",
          "https://drive.google.com/file/d/1JK_NXxCq_GhcavRTRODMKwgO6i18UNv0/view?usp=sharing"
        ]
      }
    }
  }
}